lookml_gen-0.1.9.dist-info/DESCRIPTION.rst
lookml_gen-0.1.9.dist-info/METADATA
lookml_gen-0.1.9.dist-info/RECORD
lookml_gen-0.1.9.dist-info/WHEEL
lookml_gen-0.1.9.dist-info/metadata.json
lookml_gen-0.1.9.dist-info/top_level.txt
lookmlgen/__init__.py
lookmlgen/base_generator.py
lookmlgen/field.py
lookmlgen/util.py
lookmlgen/view.py
