Metadata-Version: 2.0
Name: lookml-gen
Version: 0.1.9
Summary: Programmatically generate LookML
Home-page: https://github.com/symphonyrm/lookml-gen
Author: Joe Schmid
Author-email: jschmid@symphonyrm.com
License: Apache Software License 2.0
Keywords: lookml-gen
Platform: UNKNOWN
Classifier: Development Status :: 2 - Pre-Alpha
Classifier: Intended Audience :: Developers
Classifier: License :: OSI Approved :: Apache Software License
Classifier: Natural Language :: English
Classifier: Programming Language :: Python :: 2
Classifier: Programming Language :: Python :: 2.7
Classifier: Programming Language :: Python :: 3
Classifier: Programming Language :: Python :: 3.3
Classifier: Programming Language :: Python :: 3.4
Classifier: Programming Language :: Python :: 3.5
Requires-Dist: six (>=1.10.0)
